ormantic/__init__.py
ormantic/exceptions.py
ormantic/fields.py
ormantic/models.py
ormantic-0.0.29.data/data/LICENSE.md
ormantic-0.0.29.dist-info/LICENSE.md
ormantic-0.0.29.dist-info/METADATA
ormantic-0.0.29.dist-info/WHEEL
ormantic-0.0.29.dist-info/top_level.txt
ormantic-0.0.29.dist-info/RECORD
