Metadata-Version: 2.1
Name: ormantic
Version: 0.0.29
Summary: Async ORM + Pydantic = Ormantic ❤️
Home-page: https://github.com/awesometoolbox/ormantic
Author: Awesome Toolbox
Author-email: info@awesometoolbox.com
License: BSD
Platform: UNKNOWN
Classifier: Development Status :: 3 - Alpha
Classifier: Environment :: Web Environment
Classifier: Intended Audience :: Developers
Classifier: License :: OSI Approved :: BSD License
Classifier: Operating System :: OS Independent
Classifier: Topic :: Internet :: WWW/HTTP
Classifier: Programming Language :: Python :: 3
Classifier: Programming Language :: Python :: 3.6
Classifier: Programming Language :: Python :: 3.7
Requires-Dist: databases (>=0.2.1)
Requires-Dist: pydantic (==0.29)
